sliplib/__init__.py
sliplib/legacy.py
sliplib/slip.py
sliplib/slipserver.py
sliplib/slipsocket.py
sliplib/slipstream.py
sliplib/slipwrapper.py
sliplib-0.7.1.dist-info/METADATA
sliplib-0.7.1.dist-info/WHEEL
sliplib-0.7.1.dist-info/licenses/LICENSE
sliplib-0.7.1.dist-info/RECORD
