Metadata-Version: 2.4
Name: sliplib
Version: 0.7.1
Summary: Slip package
Project-URL: Source code, https://github.com/rhjdjong/SlipLib
Author-email: Ruud de Jong <ruud.de.jong@xs4all.nl>
License-Expression: MIT
License-File: LICENSE
Keywords: RFC1055,framing,message,protocol,slip
Classifier: Development Status :: 4 - Beta
Classifier: Intended Audience :: Developers
Classifier: License :: OSI Approved :: MIT License
Classifier: Programming Language :: Python :: 3.8
Classifier: Programming Language :: Python :: 3.9
Classifier: Programming Language :: Python :: 3.10
Classifier: Programming Language :: Python :: 3.11
Classifier: Programming Language :: Python :: 3.12
Classifier: Programming Language :: Python :: 3.13
Classifier: Topic :: Software Development :: Libraries :: Python Modules
Requires-Python: >=3.8
